mutt_ical/__init__.py
mutt_ical/viewical.py
mutt_ical-2.0.2.dist-info/LICENSE
mutt_ical-2.0.2.dist-info/METADATA
mutt_ical-2.0.2.dist-info/WHEEL
mutt_ical-2.0.2.dist-info/entry_points.txt
mutt_ical-2.0.2.dist-info/RECORD
