Metadata-Version: 2.1
Name: mutt-ical
Version: 2.0.2
Summary: Scripts for helping mutt deal with iCalendar data
Home-page: https://github.com/asciipip/mutt-ical
License: GPL-3.0-or-later
Author: Pip Gold
Author-email: pip@aperiodic.net
Requires-Python: >=3.9,<4.0
Classifier: License :: OSI Approved :: GNU General Public License v3 or later (GPLv3+)
Classifier: Programming Language :: Python :: 3
Classifier: Programming Language :: Python :: 3.9
Classifier: Programming Language :: Python :: 3.10
Classifier: Programming Language :: Python :: 3.11
Requires-Dist: icalendar (>=1.0)
Requires-Dist: tzlocal (>=3.0)
Project-URL: Repository, https://github.com/asciipip/mutt-ical
